dbp.py
dbp-18.12.3.dist-info/entry_points.txt
dbp-18.12.3.dist-info/LICENSE
dbp-18.12.3.dist-info/WHEEL
dbp-18.12.3.dist-info/METADATA
dbp-18.12.3.dist-info/RECORD
