Metadata-Version: 2.1
Name: dbp
Version: 18.12.3
Summary: Simple program to manage gbp-docker container lifecycle.
Home-page: https://openswitch.net
License: UNKNOWN
Author: Dell inc.
Author-email: opx-infra@openswitch.net
Requires-Python: >=3.5,<4
Classifier: License :: OSI Approved :: MIT License
Requires-Dist: click
Requires-Dist: controlgraph >=0.7.1
Requires-Dist: colorama
Requires-Dist: docker
Requires-Dist: networkx
Requires-Dist: pydot
Requires-Dist: mkdocs-material; extra == "doc"
Requires-Dist: pygments; extra == "doc"
Requires-Dist: pymdown-extensions; extra == "doc"
Requires-Dist: coverage; extra == "test"
Requires-Dist: pytest; extra == "test"
Requires-Dist: pytest-cov; extra == "test"
Provides-Extra: .none
Provides-Extra: doc
Provides-Extra: test
